tau_community_detection/__init__.py
tau_community_detection/algorithm.py
tau_community_detection/config.py
tau_community_detection/graph.py
tau_community_detection/partition.py
tau_community_detection-1.2.7.dist-info/METADATA
tau_community_detection-1.2.7.dist-info/WHEEL
tau_community_detection-1.2.7.dist-info/entry_points.txt
tau_community_detection-1.2.7.dist-info/top_level.txt
tau_community_detection-1.2.7.dist-info/RECORD
