Metadata-Version: 2.1
Name: tau_community_detection
Version: 1.2.7
Summary: Community detection via Louvain/Leiden + Genetic Algorithm
Author: Hillel Charbit
Author-email: hillelch@tauex.tau.ac.il
License: MIT
Classifier: Programming Language :: Python :: 3
Classifier: License :: OSI Approved :: MIT License
Classifier: Operating System :: OS Independent
Requires-Python: >=3.10
Requires-Dist: networkx ==3.2.1
Requires-Dist: numpy ==1.26.4
Requires-Dist: python-igraph ==1.0.0
Requires-Dist: scikit-learn ==1.6
